projectq/__init__.py
projectq/backends/__init__.py
projectq/backends/_printer.py
projectq/backends/_printer_test.py
projectq/backends/_resource.py
projectq/backends/_resource_test.py
projectq/backends/_aqt/__init__.py
projectq/backends/_aqt/_aqt.py
projectq/backends/_aqt/_aqt_http_client.py
projectq/backends/_aqt/_aqt_http_client_test.py
projectq/backends/_aqt/_aqt_test.py
projectq/backends/_awsbraket/__init__.py
projectq/backends/_awsbraket/_awsbraket.py
projectq/backends/_awsbraket/_awsbraket_boto3_client.py
projectq/backends/_awsbraket/_awsbraket_boto3_client_test.py
projectq/backends/_awsbraket/_awsbraket_boto3_client_test_fixtures.py
projectq/backends/_awsbraket/_awsbraket_test.py
projectq/backends/_awsbraket/_awsbraket_test_fixtures.py
projectq/backends/_circuits/__init__.py
projectq/backends/_circuits/_drawer.py
projectq/backends/_circuits/_drawer_matplotlib.py
projectq/backends/_circuits/_drawer_matplotlib_test.py
projectq/backends/_circuits/_drawer_test.py
projectq/backends/_circuits/_plot.py
projectq/backends/_circuits/_plot_test.py
projectq/backends/_circuits/_to_latex.py
projectq/backends/_circuits/_to_latex_test.py
projectq/backends/_ibm/__init__.py
projectq/backends/_ibm/_ibm.py
projectq/backends/_ibm/_ibm_http_client.py
projectq/backends/_ibm/_ibm_http_client_test.py
projectq/backends/_ibm/_ibm_test.py
projectq/backends/_ionq/__init__.py
projectq/backends/_ionq/_ionq.py
projectq/backends/_ionq/_ionq_exc.py
projectq/backends/_ionq/_ionq_http_client.py
projectq/backends/_ionq/_ionq_http_client_test.py
projectq/backends/_ionq/_ionq_mapper.py
projectq/backends/_ionq/_ionq_mapper_test.py
projectq/backends/_ionq/_ionq_test.py
projectq/backends/_sim/__init__.py
projectq/backends/_sim/_classical_simulator.py
projectq/backends/_sim/_classical_simulator_test.py
projectq/backends/_sim/_cppsim.cpython-36m-darwin.so
projectq/backends/_sim/_pysim.py
projectq/backends/_sim/_simulator.py
projectq/backends/_sim/_simulator_test.py
projectq-0.6.1.dist-info/LICENSE
projectq-0.6.1.dist-info/METADATA
projectq-0.6.1.dist-info/WHEEL
projectq-0.6.1.dist-info/top_level.txt
projectq-0.6.1.dist-info/RECORD
