Metadata-Version: 2.1
Name: projectq
Version: 0.6.1
Summary: ProjectQ - An open source software framework for quantum computing
Home-page: http://www.projectq.ch
Author: ProjectQ
Author-email: info@projectq.ch
License: Apache License Version 2.0
Project-URL: Documentation, https://projectq.readthedocs.io/en/latest/
Project-URL: Issue Tracker, https://github.com/ProjectQ-Framework/ProjectQ/
Platform: UNKNOWN
Classifier: License :: OSI Approved :: Apache Software License
Classifier: Topic :: Software Development :: Libraries :: Python Modules
Classifier: Programming Language :: Python :: 3 :: Only
Classifier: Programming Language :: Python :: 3.5
Classifier: Programming Language :: Python :: 3.6
Classifier: Programming Language :: Python :: 3.7
Classifier: Programming Language :: Python :: 3.8
Classifier: Programming Language :: Python :: 3.9
Requires-Python: >=3
License-File: LICENSE
Requires-Dist: matplotlib (>=2.2.3)
Requires-Dist: networkx (>=2)
Requires-Dist: numpy
Requires-Dist: requests
Requires-Dist: scipy
Provides-Extra: braket
Requires-Dist: boto3 ; extra == 'braket'
Provides-Extra: docs
Requires-Dist: sphinx ; extra == 'docs'
Requires-Dist: sphinx-rtd-theme ; extra == 'docs'
Provides-Extra: revkit
Requires-Dist: revkit (==3.0a2.dev2) ; extra == 'revkit'
Requires-Dist: dormouse ; extra == 'revkit'
Provides-Extra: test
Requires-Dist: flaky ; extra == 'test'
Requires-Dist: mock ; extra == 'test'
Requires-Dist: pytest (>=6.0) ; extra == 'test'
Requires-Dist: pytest-cov ; extra == 'test'
Requires-Dist: pytest-mock ; extra == 'test'
